LICENSE.txt
README.md
pyproject.toml
setup.py
src/fd58/fd58.c
src/fd58/fd58.pxd
src/fd58/fd58.pyx
src/fd58/fd_base58.c
src/fd58/fd_base58.h
src/fd58/fd_base58_tmpl.h
src/fd58.egg-info/PKG-INFO
src/fd58.egg-info/SOURCES.txt
src/fd58.egg-info/dependency_links.txt
src/fd58.egg-info/top_level.txt