Metadata-Version: 2.4
Name: fd58
Version: 0.1.1
Summary: Fast Base58 32/64 by Firedancer
Author-email: Firedancer Contributors <firedancer-devs@jumptrading.com>
Maintainer-email: Firedancer Contributors <firedancer-devs@jumptrading.com>
License:    Copyright 2024 Firedancer Contributors
Project-URL: Repository, https://github.com/firedancer-io/python-fd58.git
Project-URL: Bug Tracker, https://github.com/firedancer-io/python-fd58/issues
Classifier: Development Status :: 1 - Planning
Classifier: License :: OSI Approved :: Apache Software License
Classifier: Programming Language :: C
Classifier: Programming Language :: Cython
Requires-Python: >=3.8
License-File: LICENSE.txt
Dynamic: license-file
